{"log_count/INFO": 21, "start_time": "2025-04-16 05:51:26", "memusage/startup": 74395648, "memusage/max": 119058432, "scheduler/enqueued/memory": 499, "scheduler/enqueued": 499, "scheduler/dequeued/memory": 499, "scheduler/dequeued": 499, "downloader/request_count": 526, "downloader/request_method_count/GET": 526, "downloader/request_bytes": 208211, "downloader/response_count": 526, "downloader/response_status_count/200": 499, "downloader/response_bytes": 9220857, "httpcompression/response_bytes": 47024607, "httpcompression/response_count": 499, "response_received_count": 526, "log_count/WARNING": 526, "request_depth_max": 439, "file_count": 1, "file_status_count/uptodate": 1, "item_scraped_count": 59, "downloader/response_status_count/301": 27, "elapsed_time_seconds": 550.17566, "finish_time": "2025-04-16 06:00:36", "finish_reason": "finished"}