{"log_count/INFO": 11, "start_time": "2023-08-08 05:51:46", "memusage/startup": 78966784, "memusage/max": 78966784, "scheduler/enqueued/memory": 24, "scheduler/enqueued": 24, "scheduler/dequeued/memory": 24, "scheduler/dequeued": 24, "downloader/request_count": 27, "downloader/request_method_count/GET": 27, "downloader/request_bytes": 10295, "downloader/response_count": 27, "downloader/response_status_count/200": 27, "downloader/response_bytes": 2060923, "httpcompression/response_bytes": 3626796, "httpcompression/response_count": 24, "response_received_count": 27, "log_count/WARNING": 13, "file_count": 179, "file_status_count/uptodate": 176, "request_depth_max": 1, "item_scraped_count": 208, "file_status_count/downloaded": 3, "elapsed_time_seconds": 4.711089, "finish_time": "2023-08-08 05:51:51", "finish_reason": "finished"}