{"log_count/INFO": 11, "start_time": "2023-03-14 01:18:40", "memusage/startup": 75894784, "memusage/max": 75894784, "scheduler/enqueued/memory": 209, "scheduler/enqueued": 209, "scheduler/dequeued/memory": 209, "scheduler/dequeued": 209, "downloader/request_count": 209, "downloader/request_method_count/GET": 209, "downloader/request_bytes": 80450, "downloader/response_count": 209, "downloader/response_status_count/200": 209, "downloader/response_bytes": 8652949, "httpcompression/response_bytes": 33003880, "httpcompression/response_count": 209, "response_received_count": 209, "request_depth_max": 1, "file_count": 173, "file_status_count/uptodate": 173, "item_scraped_count": 208, "elapsed_time_seconds": 4.01899, "finish_time": "2023-03-14 01:18:44", "finish_reason": "finished"}