{"log_count/INFO": 12, "start_time": "2024-10-04 05:51:52", "memusage/startup": 79228928, "memusage/max": 79228928, "scheduler/enqueued/memory": 7, "scheduler/enqueued": 7, "scheduler/dequeued/memory": 7, "scheduler/dequeued": 7, "downloader/request_count": 11, "downloader/request_method_count/GET": 11, "downloader/request_bytes": 4066, "downloader/response_count": 11, "downloader/response_status_count/200": 7, "downloader/response_bytes": 205695, "httpcompression/response_bytes": 903270, "httpcompression/response_count": 7, "response_received_count": 11, "log_count/WARNING": 9, "file_count": 174, "file_status_count/uptodate": 174, "request_depth_max": 1, "item_scraped_count": 209, "downloader/response_status_count/301": 4, "elapsed_time_seconds": 0.645909, "finish_time": "2024-10-04 05:51:53", "finish_reason": "finished"}