{"log_count/INFO": 12, "start_time": "2024-10-11 05:52:06", "memusage/startup": 79446016, "memusage/max": 79446016, "scheduler/enqueued/memory": 5, "scheduler/enqueued": 5, "scheduler/dequeued/memory": 5, "scheduler/dequeued": 5, "downloader/request_count": 9, "downloader/request_method_count/GET": 9, "downloader/request_bytes": 3294, "downloader/response_count": 9, "downloader/response_status_count/200": 5, "downloader/response_bytes": 140207, "httpcompression/response_bytes": 645609, "httpcompression/response_count": 5, "response_received_count": 9, "log_count/WARNING": 9, "file_count": 174, "file_status_count/uptodate": 174, "request_depth_max": 1, "downloader/response_status_count/301": 4, "item_scraped_count": 208, "elapsed_time_seconds": 2.041156, "finish_time": "2024-10-11 05:52:08", "finish_reason": "finished"}