{"log_count/INFO": 11, "start_time": "2024-01-10 05:51:24", "memusage/startup": 76877824, "memusage/max": 76877824, "scheduler/enqueued/memory": 17, "scheduler/enqueued": 17, "scheduler/dequeued/memory": 17, "scheduler/dequeued": 17, "downloader/request_count": 20, "downloader/request_method_count/GET": 20, "downloader/request_bytes": 7784, "downloader/response_count": 20, "downloader/response_status_count/200": 19, "downloader/response_bytes": 805047, "httpcompression/response_bytes": 1898637, "httpcompression/response_count": 9, "response_received_count": 20, "log_count/WARNING": 5, "file_count": 318, "file_status_count/uptodate": 315, "request_depth_max": 2, "item_scraped_count": 173, "file_status_count/downloaded": 3, "downloader/response_status_count/404": 1, "log_count/ERROR": 1, "elapsed_time_seconds": 3.031865, "finish_time": "2024-01-10 05:51:27", "finish_reason": "finished"}