{"log_count/INFO": 12, "start_time": "2024-02-15 05:51:38", "memusage/startup": 77602816, "memusage/max": 77602816, "scheduler/enqueued/memory": 17, "scheduler/enqueued": 17, "scheduler/dequeued/memory": 17, "scheduler/dequeued": 17, "downloader/request_count": 17, "downloader/request_method_count/GET": 17, "downloader/request_bytes": 6535, "downloader/response_count": 17, "downloader/response_status_count/200": 17, "downloader/response_bytes": 596628, "httpcompression/response_bytes": 2031478, "httpcompression/response_count": 9, "response_received_count": 17, "log_count/WARNING": 5, "file_count": 352, "file_status_count/uptodate": 352, "request_depth_max": 2, "item_scraped_count": 186, "elapsed_time_seconds": 1.822202, "finish_time": "2024-02-15 05:51:40", "finish_reason": "finished"}