{"log_count/INFO": 12, "start_time": "2024-06-06 05:53:16", "memusage/startup": 77705216, "memusage/max": 77705216, "scheduler/enqueued/memory": 17, "scheduler/enqueued": 17, "scheduler/dequeued/memory": 17, "scheduler/dequeued": 17, "downloader/request_count": 29, "downloader/request_method_count/GET": 29, "downloader/request_bytes": 11420, "downloader/response_count": 29, "downloader/response_status_count/200": 28, "downloader/response_bytes": 1675329, "httpcompression/response_bytes": 2050833, "httpcompression/response_count": 9, "response_received_count": 29, "log_count/WARNING": 6, "file_count": 342, "file_status_count/uptodate": 331, "request_depth_max": 2, "item_scraped_count": 177, "file_status_count/downloaded": 11, "downloader/response_status_count/302": 1, "log_count/ERROR": 2, "elapsed_time_seconds": 1.753912, "finish_time": "2024-06-06 05:53:18", "finish_reason": "finished"}