{"log_count/INFO": 11, "start_time": "2023-03-18 05:51:48", "memusage/startup": 75931648, "memusage/max": 75931648, "scheduler/enqueued/memory": 17, "scheduler/enqueued": 17, "scheduler/dequeued/memory": 17, "scheduler/dequeued": 17, "downloader/request_count": 17, "downloader/request_method_count/GET": 17, "downloader/request_bytes": 6381, "downloader/response_count": 17, "downloader/response_status_count/200": 13, "downloader/response_bytes": 434100, "httpcompression/response_bytes": 1645808, "httpcompression/response_count": 9, "response_received_count": 17, "file_count": 275, "file_status_count/uptodate": 275, "request_depth_max": 2, "item_scraped_count": 143, "downloader/response_status_count/404": 4, "log_count/ERROR": 1, "elapsed_time_seconds": 3.800447, "finish_time": "2023-03-18 05:51:52", "finish_reason": "finished"}