{"log_count/INFO": 12, "start_time": "2024-03-30 05:51:19", "memusage/startup": 77299712, "memusage/max": 77299712, "scheduler/enqueued/memory": 17, "scheduler/enqueued": 17, "scheduler/dequeued/memory": 17, "scheduler/dequeued": 17, "downloader/request_count": 39, "downloader/request_method_count/GET": 39, "downloader/request_bytes": 15592, "downloader/response_count": 39, "downloader/response_status_count/200": 27, "downloader/response_bytes": 2190677, "httpcompression/response_bytes": 1824310, "httpcompression/response_count": 9, "response_received_count": 39, "log_count/WARNING": 14, "file_count": 267, "file_status_count/uptodate": 256, "downloader/response_status_count/302": 11, "request_depth_max": 2, "item_scraped_count": 149, "file_status_count/downloaded": 11, "downloader/response_status_count/404": 1, "elapsed_time_seconds": 3.652058, "finish_time": "2024-03-30 05:51:22", "finish_reason": "finished"}