{"log_count/INFO": 12, "start_time": "2024-02-06 05:51:28", "memusage/startup": 77852672, "memusage/max": 77852672, "scheduler/enqueued/memory": 17, "scheduler/enqueued": 17, "scheduler/dequeued/memory": 17, "scheduler/dequeued": 17, "downloader/request_count": 23, "downloader/request_method_count/GET": 23, "downloader/request_bytes": 8994, "downloader/response_count": 23, "downloader/response_status_count/200": 23, "downloader/response_bytes": 1328636, "httpcompression/response_bytes": 2033918, "httpcompression/response_count": 9, "response_received_count": 23, "log_count/WARNING": 6, "file_count": 360, "file_status_count/uptodate": 354, "request_depth_max": 2, "item_scraped_count": 194, "file_status_count/downloaded": 6, "elapsed_time_seconds": 3.668731, "finish_time": "2024-02-06 05:51:32", "finish_reason": "finished"}